sharething/__init__.py
sharething/babel.py
sharething/bcrypt.py
sharething/cache.py
sharething/login.py
sharething/mail.py
sharething/migrate.py
sharething/oauth.py
sharething/redis.py
sharething/restful.py
sharething/sqlalchemy.py
sharething/user.py
sharething-0.1.0.dist-info/LICENSE
sharething-0.1.0.dist-info/METADATA
sharething-0.1.0.dist-info/WHEEL
sharething-0.1.0.dist-info/top_level.txt
sharething-0.1.0.dist-info/RECORD
